shippo/__init__.py
shippo/api_requestor.py
shippo/certificate_blacklist.py
shippo/config.py
shippo/error.py
shippo/http_client.py
shippo/resource.py
shippo/util.py
shippo/version.py
shippo/test/__init__.py
shippo/test/helper.py
shippo/test/test_address.py
shippo/test/test_api_requestor.py
shippo/test/test_batch.py
shippo/test/test_customs_declaration.py
shippo/test/test_customs_item.py
shippo/test/test_http_client.py
shippo/test/test_manifest.py
shippo/test/test_order.py
shippo/test/test_parcel.py
shippo/test/test_pickup.py
shippo/test/test_rate.py
shippo/test/test_shipment.py
shippo/test/test_track.py
shippo/test/test_transaction.py
shippo/test/integration/__init__.py
shippo/test/integration/test_integration.py
shippo_mwisslead-2.1.3.dev1.dist-info/LICENSE
shippo_mwisslead-2.1.3.dev1.dist-info/METADATA
shippo_mwisslead-2.1.3.dev1.dist-info/WHEEL
shippo_mwisslead-2.1.3.dev1.dist-info/top_level.txt
shippo_mwisslead-2.1.3.dev1.dist-info/RECORD
