Metadata-Version: 2.1
Name: shippo-mwisslead
Version: 2.1.3.dev1
Summary: Shipping API Python library (USPS, FedEx, UPS and more) forked to remove requirements restrictions
Home-page: https://goshippo.com/
Author: Shippo
Author-email: support@goshippo.com
Classifier: Development Status :: 5 - Production/Stable
Classifier: Intended Audience :: Developers
Classifier: License :: OSI Approved :: MIT License
Classifier: Operating System :: OS Independent
Classifier: Programming Language :: Python
Classifier: Programming Language :: Python :: 3.5
Classifier: Programming Language :: Python :: 3.6
Classifier: Programming Language :: Python :: 3.7
Classifier: Programming Language :: Python :: 3 :: Only
Classifier: Programming Language :: Python :: Implementation :: PyPy
Classifier: Topic :: Software Development :: Libraries :: Python Modules
License-File: LICENSE
Requires-Dist: requests
Requires-Dist: simplejson (>=3.16.0)
